bids/__init__.py
bids/analyser.py
bids/bids-search.py
bids/callgraph.py
bids/cli.py
bids/elf_utils.py
bids/index.py
bids/library.py
bids/output.py
bids/sbom.py
bids/sbom4bids.py
bids/scan.py
bids/search.py
bids/util.py
bids/version.py
playground/__init__.py
playground/bids-search.py
playground/index.py
test/__init__.py
test/test_analyser.py
test/test_cli.py
test/test_elf_utils.py
test/test_index.py
test/test_library.py
test/test_output.py
test/test_sbom.py
test/test_scan.py
test/test_search.py
tests/__init__.py
tests/test_cli.py
bids_analyser-0.2.0.dist-info/LICENSE
bids_analyser-0.2.0.dist-info/METADATA
bids_analyser-0.2.0.dist-info/NOTICE
bids_analyser-0.2.0.dist-info/WHEEL
bids_analyser-0.2.0.dist-info/entry_points.txt
bids_analyser-0.2.0.dist-info/top_level.txt
bids_analyser-0.2.0.dist-info/RECORD
