Metadata-Version: 2.1
Name: bids-analyser
Version: 0.2.0
Summary: Analyser for ELF files
Home-page: https://github.com/aph10/BIDS
Author: Anthony Harrison
Author-email: anthony@aph10.com
Maintainer: Anthony Harrison
Maintainer-email: anthony@aph10.com
License: Apache-2.0
Keywords: security,tools,ELF,Dependency,Symbols,Binary Analsyis
Classifier: Development Status :: 3 - Alpha
Classifier: Intended Audience :: Developers
Classifier: License :: OSI Approved :: Apache Software License
Classifier: Natural Language :: English
Classifier: Operating System :: OS Independent
Classifier: Programming Language :: Python :: 3.9
Classifier: Programming Language :: Python :: 3.10
Classifier: Programming Language :: Python :: 3.11
Classifier: Programming Language :: Python :: 3.12
Classifier: Programming Language :: Python :: 3.13
Classifier: Programming Language :: Python :: Implementation :: CPython
Classifier: Programming Language :: Python :: Implementation :: PyPy
Requires-Python: >=3.9
License-File: LICENSE
License-File: NOTICE
Requires-Dist: pyelftools
Requires-Dist: lib4sbom
Requires-Dist: tantivy
Requires-Dist: typecode[full] ; python_version < "3.10"
Requires-Dist: typecode-libmagic-system-provided ; python_version >= "3.10"
Requires-Dist: typecode ; python_version >= "3.10"
